geo_data/__init__.py
geo_data/admin.py
geo_data/apps.py
geo_data/database.py
geo_data/middleware.py
geo_data/models.py
geo_data/task.py
geo_data/tests.py
geo_data/urls.py
geo_data/utility.py
geo_data/views.py
geo_data/migrations/0001_initial.py
geo_data/migrations/0002_geo_data_ip_init.py
geo_data/migrations/0003_geodata_delete_geo_data.py
geo_data/migrations/0004_delete_geodata.py
geo_data/migrations/__init__.py
django_geoinfo-0.1.0.dist-info/LICENSE
django_geoinfo-0.1.0.dist-info/METADATA
django_geoinfo-0.1.0.dist-info/WHEEL
django_geoinfo-0.1.0.dist-info/top_level.txt
django_geoinfo-0.1.0.dist-info/RECORD
